avatar_handler/__init__.py
avatar_handler-1.0.0.dist-info/METADATA
avatar_handler-1.0.0.dist-info/WHEEL
avatar_handler-1.0.0.dist-info/top_level.txt
avatar_handler-1.0.0.dist-info/RECORD
