Metadata-Version: 2.4
Name: avatar_handler
Version: 1.0.0
Summary: A library for handling and setting user avatars from various sources.
Author: A.H. Team
Requires-Dist: requests
Requires-Dist: Pillow
Dynamic: author
Dynamic: requires-dist
Dynamic: summary
